pyxbos/__init__.py
pyxbos/brick_pb2.py
pyxbos/brick_pb2_grpc.py
pyxbos/c37_pb2.py
pyxbos/c37_pb2_grpc.py
pyxbos/dentmeter_pb2.py
pyxbos/dentmeter_pb2_grpc.py
pyxbos/driver.py
pyxbos/drivers/__init__.py
pyxbos/drivers/bacnet/bacnet.py
pyxbos/drivers/bacnet/buildings/orinda-public-library/point_to_class.json
pyxbos/drivers/bacnet/buildings/orinda-public-library/point_to_value.json
pyxbos/drivers/bacnet/buildings/orinda-public-library/point_values_by_equipment.json
pyxbos/drivers/dark_sky/dark_sky.py
pyxbos/drivers/hue/hue.py
pyxbos/drivers/hue/requirements.txt
pyxbos/drivers/obvius/obvius.py
pyxbos/drivers/obvius/obvius.yaml
pyxbos/drivers/obvius/requirements.txt
pyxbos/drivers/obvius/sensordb.py
pyxbos/drivers/parker/parker.py
pyxbos/drivers/parker/parker.yaml
pyxbos/drivers/pbc/__init__.py
pyxbos/drivers/pbc/pbc_framework.py
pyxbos/drivers/system_monitor/requirements.txt
pyxbos/drivers/system_monitor/systemmonitor.py
pyxbos/drivers/weather_current/weather_current.py
pyxbos/drivers/weather_prediction/weather_prediction.py
pyxbos/eapi_pb2.py
pyxbos/eapi_pb2_grpc.py
pyxbos/energise_pb2.py
pyxbos/energise_pb2_grpc.py
pyxbos/energize_pb2.py
pyxbos/energize_pb2_grpc.py
pyxbos/exceptions.py
pyxbos/grpcserver_pb2.py
pyxbos/grpcserver_pb2_grpc.py
pyxbos/hamilton_pb2.py
pyxbos/hamilton_pb2_grpc.py
pyxbos/helloworld_pb2.py
pyxbos/hvac_pb2.py
pyxbos/hvac_pb2_grpc.py
pyxbos/iot_pb2.py
pyxbos/iot_pb2_grpc.py
pyxbos/mortard.py
pyxbos/nullabletypes_pb2.py
pyxbos/nullabletypes_pb2_grpc.py
pyxbos/parker_pb2.py
pyxbos/parker_pb2_grpc.py
pyxbos/process.py
pyxbos/system_monitor_pb2.py
pyxbos/system_monitor_pb2_grpc.py
pyxbos/wave/eapi.proto
pyxbos/wave/eapi_pb2.py
pyxbos/wave/eapi_pb2_grpc.py
pyxbos/wavemq/eapi.proto
pyxbos/wavemq/wavemq.proto
pyxbos/wavemq_pb2.py
pyxbos/wavemq_pb2_grpc.py
pyxbos/weather_station_pb2.py
pyxbos/weather_station_pb2_grpc.py
pyxbos/xbos_pb2.py
pyxbos/xbos_pb2_grpc.py
pyxbos-0.2.33.dist-info/WHEEL
pyxbos-0.2.33.dist-info/METADATA
pyxbos-0.2.33.dist-info/RECORD
